sequal/__init__.py
sequal/amino_acid.py
sequal/base_block.py
sequal/ion.py
sequal/mass.py
sequal/mass_spectrometry.py
sequal/modification.py
sequal/proforma.py
sequal/resources.py
sequal/sequence.py
sequal-2.0.4.dist-info/LICENSE
sequal-2.0.4.dist-info/METADATA
sequal-2.0.4.dist-info/WHEEL
sequal-2.0.4.dist-info/RECORD
