Metadata-Version: 2.1
Name: sequal
Version: 2.0.4
Summary: A Python package for working with protein sequence and PTM
License: MIT
Keywords: protein sequence,modification,mass spectrometry
Author: Toan K. Phung
Author-email: toan.phungkhoiquoctoan@gmail.com
Requires-Python: >=3.9,<4.0
Classifier: License :: OSI Approved :: MIT License
Classifier: Programming Language :: Python :: 3
Classifier: Programming Language :: Python :: 3.9
Classifier: Programming Language :: Python :: 3.10
Classifier: Programming Language :: Python :: 3.11
Classifier: Programming Language :: Python :: 3.12
